[{"__type__":"cc.AnimationClip","_name":"rockbomb","_duration":0.25,"curveData":{"comps":{"cc.Sprite":{"spriteFrame":[{"frame":0,"value":{"__uuid__":"434TNNcR1PfJr8GJedeD7D"}},{"frame":0.08333333333333333,"value":{"__uuid__":"e1ohDKGppE16sUMCyd//JL"}},{"frame":0.16666666666666666,"value":{"__uuid__":"e1ohDKGppE16sUMCyd//JL"}}]}},"props":{"opacity":[{"frame":0,"value":255},{"frame":0.16666666666666666,"value":255},{"frame":0.25,"value":0}]}},"events":[{"frame":0.25,"func":"bombOver","params":[]}]},{"__type__":"cc.SpriteFrame","content":{"name":"rock","texture":"e8KXBEhTZHF7Dvc30sZSW5","rect":[0,0,1152,700],"offset":[0,0],"originalSize":[1152,700],"capInsets":[0,0,0,0]}},{"__type__":"cc.AudioClip","_name":"bomb","_native":".mp3"},[{"__type__":"cc.Prefab","_name":"smallRock","data":{"__id__":1}},{"__type__":"cc.Node","_name":"smallRock","_level":2,"_components":[{"__type__":"cc.Sprite","node":{"__id__":1},"_spriteFrame":{"__uuid__":"434TNNcR1PfJr8GJedeD7D"},"_sizeMode":0},{"__type__":"cc.PolygonCollider","node":{"__id__":1},"points":[{"__type__":"cc.Vec2","x":-14.987847222222221,"y":16.792714285714283},{"__type__":"cc.Vec2","x":-22.734375,"y":10.640428571428572},{"__type__":"cc.Vec2","x":-19.576822916666664,"y":3.2274285714285718},{"__type__":"cc.Vec2","x":-20.37673611111111,"y":-3.630857142857142},{"__type__":"cc.Vec2","x":-23.239583333333332,"y":-5.143714285714285},{"__type__":"cc.Vec2","x":-22.608072916666668,"y":-14.220857142857142},{"__type__":"cc.Vec2","x":-21.21875,"y":-17.145714285714284},{"__type__":"cc.Vec2","x":-9.556857638888888,"y":-14.573857142857142},{"__type__":"cc.Vec2","x":-7.19921875,"y":-15.733714285714285},{"__type__":"cc.Vec2","x":-1.8103298611111107,"y":-10.842142857142857},{"__type__":"cc.Vec2","x":-2.020833333333332,"y":-13.867857142857142},{"__type__":"cc.Vec2","x":-0.7578125,"y":-15.22942857142857},{"__type__":"cc.Vec2","x":6.0625000000000036,"y":-15.22942857142857},{"__type__":"cc.Vec2","x":9.725260416666671,"y":-16.893571428571427},{"__type__":"cc.Vec2","x":12.040798611111114,"y":-14.775571428571428},{"__type__":"cc.Vec2","x":21.134548611111114,"y":-11.850714285714284},{"__type__":"cc.Vec2","x":21.42925347222223,"y":-7.059999999999999},{"__type__":"cc.Vec2","x":23.828993055555557,"y":-2.218857142857143},{"__type__":"cc.Vec2","x":17.68229166666667,"y":8.925857142857144},{"__type__":"cc.Vec2","x":10.861979166666671,"y":13.111428571428572},{"__type__":"cc.Vec2","x":7.704427083333336,"y":13.918285714285716},{"__type__":"cc.Vec2","x":3.9153645833333357,"y":11.043857142857142},{"__type__":"cc.Vec2","x":1.5998263888888893,"y":11.043857142857142},{"__type__":"cc.Vec2","x":-4.16796875,"y":16.18757142857143}]},{"__type__":"09721syMk9Jq7F6JuEK2Vzy","node":{"__id__":1},"speed":3,"value":5},{"__type__":"cc.Animation","node":{"__id__":1},"_defaultClip":{"__uuid__":"41FUe1TEdDXr9/ygKFS59Z"},"_clips":[{"__uuid__":"41FUe1TEdDXr9/ygKFS59Z"}]}],"_prefab":{"__type__":"cc.PrefabInfo","root":{"__id__":1},"asset":{"__uuid__":"bbJ63qFp9N1rxpsrYLq5KD"},"fileId":"db4tVfskRBN73RVTr7GIQc"},"_contentSize":{"__type__":"cc.Size","width":48.5,"height":35.3},"_position":{"__type__":"cc.Vec3","x":129,"y":-29},"groupIndex":2}],{"__type__":"cc.SpriteFrame","content":{"name":"bomb1","texture":"72OpKhr7hJ5ZP5iSv9pz4h","rect":[0,0,662,520],"offset":[0,0],"originalSize":[662,520],"capInsets":[0,0,0,0]}}]